setup.py
meme/__init__.py
meme/meme.py
meme_py.egg-info/PKG-INFO
meme_py.egg-info/SOURCES.txt
meme_py.egg-info/dependency_links.txt
meme_py.egg-info/requires.txt
meme_py.egg-info/top_level.txt