Metadata-Version: 1.0
Name: meme-py
Version: 0.3.0
Summary: Yahoo! Meme (http://meme.yahoo.com) client API.
Home-page: http://github.com/guilhermechapiewski/meme-py/
Author: Guilherme Chapiewski and friends
Author-email: guilherme.chapiewski@gmail.com
License: Apache License 2.0
Keywords: yahoo meme client api
Platform: UNKNOWN
